CONTRIBUTING.md
MANIFEST.in
README.rst
setup.py
docs/HISTORY.txt
docs/LICENSE.GPL
docs/LICENSE.txt
eea/__init__.py
eea.jquery.egg-info/PKG-INFO
eea.jquery.egg-info/SOURCES.txt
eea.jquery.egg-info/dependency_links.txt
eea.jquery.egg-info/entry_points.txt
eea.jquery.egg-info/namespace_packages.txt
eea.jquery.egg-info/not-zip-safe
eea.jquery.egg-info/requires.txt
eea.jquery.egg-info/top_level.txt
eea/jquery/README.txt
eea/jquery/__init__.py
eea/jquery/common.zcml
eea/jquery/configure.zcml
eea/jquery/plone.zcml
eea/jquery/profiles-bbb.zcml
eea/jquery/profiles.zcml
eea/jquery/testing.zcml
eea/jquery/version.txt
eea/jquery/zope2.zcml
eea/jquery/browser/__init__.py
eea/jquery/browser/configure.zcml
eea/jquery/browser/images/ajax-loader.gif
eea/jquery/jquery/__init__.py
eea/jquery/jquery/configure.zcml
eea/jquery/jquery/jquery-1.4.4.js
eea/jquery/jquery/jquery-1.7.2.js
eea/jquery/jquery/jquery.css
eea/jquery/plugins/__init__.py
eea/jquery/plugins/configure.zcml
eea/jquery/plugins/ajaxfileupload/jquery.ajaxfileupload.js
eea/jquery/plugins/annotator/annotator-full.js
eea/jquery/plugins/annotator/annotator.css
eea/jquery/plugins/annotator/update.sh
eea/jquery/plugins/bbq/jquery.ba-bbq.min.js
eea/jquery/plugins/browser/jquery.browser.min.js
eea/jquery/plugins/colorpicker/css/colorpicker.css
eea/jquery/plugins/colorpicker/images/blank.gif
eea/jquery/plugins/colorpicker/images/colorpicker_background.png
eea/jquery/plugins/colorpicker/images/colorpicker_hex.png
eea/jquery/plugins/colorpicker/images/colorpicker_hsb_b.png
eea/jquery/plugins/colorpicker/images/colorpicker_hsb_h.png
eea/jquery/plugins/colorpicker/images/colorpicker_hsb_s.png
eea/jquery/plugins/colorpicker/images/colorpicker_indic.gif
eea/jquery/plugins/colorpicker/images/colorpicker_overlay.png
eea/jquery/plugins/colorpicker/images/colorpicker_rgb_b.png
eea/jquery/plugins/colorpicker/images/colorpicker_rgb_g.png
eea/jquery/plugins/colorpicker/images/colorpicker_rgb_r.png
eea/jquery/plugins/colorpicker/images/colorpicker_select.gif
eea/jquery/plugins/colorpicker/images/colorpicker_submit.png
eea/jquery/plugins/colorpicker/images/custom_background.png
eea/jquery/plugins/colorpicker/images/custom_hex.png
eea/jquery/plugins/colorpicker/images/custom_hsb_b.png
