Metadata-Version: 2.4
Name: eea.jquery
Version: 11.4
Summary: jQuery library and plugins for Plone
Home-page: https://github.com/eea/eea.jquery
Download-URL: https://pypi.python.org/pypi/eea.jquery
Author: European Environment Agency: IDM2 A-Team
Author-email: eea-edw-a-team-alerts@googlegroups.com
License: GPL
Keywords: EEA jquery plugins Add-ons Plone Zope
Classifier: Framework :: Zope2
Classifier: Framework :: Plone
Classifier: Framework :: Plone :: 4.0
Classifier: Framework :: Plone :: 4.1
Classifier: Framework :: Plone :: 4.2
Classifier: Framework :: Plone :: 4.3
Classifier: Programming Language :: Zope
Classifier: Programming Language :: Python
Classifier: Programming Language :: Python :: 2.7
Classifier: Topic :: Software Development :: Libraries :: Python Modules
Classifier: License :: OSI Approved :: GNU General Public License (GPL)
Requires-Dist: setuptools
Requires-Dist: collective.js.jqueryui
Provides-Extra: test
Requires-Dist: plone.app.testing; extra == "test"
Provides-Extra: zope2
Dynamic: author
Dynamic: author-email
Dynamic: classifier
Dynamic: description
Dynamic: description-content-type
Dynamic: download-url
Dynamic: home-page
Dynamic: keywords
Dynamic: license
Dynamic: provides-extra
Dynamic: requires-dist
Dynamic: summary
